pretix_nets_easy/__init__.py
pretix_nets_easy/apps.py
pretix_nets_easy/forms.py
pretix_nets_easy/payment.py
pretix_nets_easy/signals.py
pretix_nets_easy/urls.py
pretix_nets_easy/views.py
pretix_nets_easy/locale/django.pot
pretix_nets_easy/locale/da/LC_MESSAGES/django.mo
pretix_nets_easy/locale/da/LC_MESSAGES/django.po
pretix_nets_easy/locale/de/LC_MESSAGES/django.mo
pretix_nets_easy/locale/de/LC_MESSAGES/django.po
pretix_nets_easy/locale/de_Informal/.gitkeep
pretix_nets_easy/locale/de_Informal/LC_MESSAGES/django.mo
pretix_nets_easy/locale/de_Informal/LC_MESSAGES/django.po
pretix_nets_easy/static/pretix_nets_easy/.gitkeep
pretix_nets_easy/static/pretix_nets_easy/logo.svg
pretix_nets_easy/static/pretix_nets_easy/pretix_nets_easy.js
pretix_nets_easy/templates/pretix_nets_easy/.gitkeep
pretix_nets_easy/templates/pretix_nets_easy/checkout_payment_confirm.html
pretix_nets_easy/templates/pretix_nets_easy/checkout_payment_form.html
pretix_nets_easy/templates/pretix_nets_easy/control.html
pretix_nets_easy/templates/pretix_nets_easy/pay.html
pretix_nets_easy-1.0.0.dist-info/licenses/LICENSE
pretix_nets_easy-1.0.0.dist-info/METADATA
pretix_nets_easy-1.0.0.dist-info/WHEEL
pretix_nets_easy-1.0.0.dist-info/entry_points.txt
pretix_nets_easy-1.0.0.dist-info/top_level.txt
pretix_nets_easy-1.0.0.dist-info/RECORD
