Metadata-Version: 2.4
Name: pretix-nets-easy
Version: 1.0.0
Summary: Accept payments through the nets (formerly DIBS) Easy payment gateway
Author-email: pretix team <support@pretix.eu>
Maintainer-email: pretix team <support@pretix.eu>
License: 
Project-URL: homepage, https://code.rami.io/pretix/pretix-nets-easy/
Keywords: pretix
Requires-Python: >=3.9
License-File: LICENSE
Dynamic: license-file
